{"name":"ChineseTakeaway","type":"TTF","desc":{"CapHeight":803,"XHeight":803,"FontBBox":"[-6 -200 1028 808]","Flags":4,"Ascent":805,"Descent":-200,"Leading":0,"ItalicAngle":0,"StemV":87,"MissingWidth":500},"unitsPerEm":1000,"up":-133,"ut":20,"strp":259,"strs":50,"ttffile":"C:\\xampp\\htdocs\\College\\Year 2\\WEBFS\\DeGoudenDraak_Development\\public\\\/fonts\/main.ttf","TTCfontID":0,"originalsize":29000,"sip":false,"smp":false,"BMPselected":false,"fontkey":"main","panose":" 0 0 0 0 4 0 0 0 0 0 0 0","haskerninfo":false,"haskernGPOS":false,"hassmallcapsGSUB":false,"fontmetrics":"win","useOTL":0,"rtlPUAstr":"","GSUBScriptLang":[],"GSUBFeatures":[],"GSUBLookups":[],"GPOSScriptLang":[],"GPOSFeatures":[],"GPOSLookups":[],"kerninfo":[]}